autotuner_core/__init__.py
autotuner_core/algorithms/__init__.py
autotuner_core/algorithms/graphs/__init__.py
autotuner_core/algorithms/graphs/bfs.py
autotuner_core/algorithms/graphs/cycle_detection.py
autotuner_core/algorithms/graphs/dfs.py
autotuner_core/algorithms/graphs/dijkstra_heap.py
autotuner_core/algorithms/graphs/dijkstra_matrix.py
autotuner_core/algorithms/graphs/toposort.py
autotuner_core/algorithms/graphs/union_find.py
autotuner_core/algorithms/sorting/__init__.py
autotuner_core/algorithms/sorting/counting_sort.py
autotuner_core/algorithms/sorting/insertion_sort.py
autotuner_core/algorithms/sorting/merge_sort.py
autotuner_core/algorithms/sorting/quick_sort.py
autotuner_core/algorithms/sorting/timsort.py
autotuner_core/autotuner/__init__.py
autotuner_core/autotuner/benchmark.py
autotuner_core/autotuner/features.py
autotuner_core/autotuner/graph_features.py
autotuner_core/autotuner/graph_switcher.py
autotuner_core/autotuner/logger.py
autotuner_core/autotuner/switcher.py
autotuner_core/autotuner/visualizer.py
autotuner_core/cli/__init__.py
autotuner_core/cli/graph_cli.py
autotuner_core/cli/sort_cli.py
autotuner_core-0.1.1.dist-info/licenses/LICENSE
autotuner_core-0.1.1.dist-info/METADATA
autotuner_core-0.1.1.dist-info/WHEEL
autotuner_core-0.1.1.dist-info/entry_points.txt
autotuner_core-0.1.1.dist-info/top_level.txt
autotuner_core-0.1.1.dist-info/RECORD
