Metadata-Version: 2.4
Name: autotuner_core
Version: 0.1.1
Summary: AutoTuner: A Self-Optimizing Algorithm Engine
Home-page: https://github.com/koushik-mahamkali/autotuner
Author: Krishna Koushik
Author-email: Koushik Mahamkali <mahamkalikoushik0@gmail.com>
License: MIT
Project-URL: Homepage, https://github.com/koushik-mahamkali/autotuner
Project-URL: Documentation, https://github.com/koushik-mahamkali/autotuner#readme
Project-URL: Source, https://github.com/koushik-mahamkali/autotuner
Requires-Python: >=3.7
License-File: LICENSE
Requires-Dist: numpy
Requires-Dist: matplotlib
Requires-Dist: networkx
Requires-Dist: mplcyberpunk
Requires-Dist: pandas
Requires-Dist: seaborn
Dynamic: author
Dynamic: home-page
Dynamic: license-file
Dynamic: requires-python
